torch_kf/__init__.py
torch_kf/ckf.py
torch_kf/kalman_filter.py
torch_kf/py.typed
torch_kf-0.4.1.dist-info/licenses/LICENSE
torch_kf-0.4.1.dist-info/WHEEL
torch_kf-0.4.1.dist-info/METADATA
torch_kf-0.4.1.dist-info/RECORD
