Metadata-Version: 2.4
Name: torch-kf
Version: 0.4.1
Summary: Kalman Filter implementation with PyTorch
Keywords: Kalman filter,PyTorch,Statistics
Author: Raphael Reme
Author-email: Raphael Reme <raphaelreme-dev@protonmail.com>
License-Expression: MIT
License-File: LICENSE
Classifier: Development Status :: 4 - Beta
Classifier: License :: OSI Approved :: MIT License
Classifier: Natural Language :: English
Classifier: Operating System :: OS Independent
Classifier: Programming Language :: Python :: 3.9
Classifier: Programming Language :: Python :: 3.10
Classifier: Programming Language :: Python :: 3.11
Classifier: Programming Language :: Python :: 3.12
Classifier: Programming Language :: Python :: 3.13
Requires-Dist: torch
Maintainer: Raphael Reme
Maintainer-email: Raphael Reme <raphaelreme-dev@protonmail.com>
Requires-Python: >=3.9
Project-URL: Documentation, https://github.com/raphaelreme/torch-kf
Project-URL: Homepage, https://github.com/raphaelreme/torch-kf
Project-URL: Issues, https://github.com/raphaelreme/torch-kf/issues
Project-URL: Repository, https://github.com/raphaelreme/torch-kf
